cityhero/__init__.py
cityhero-0.0.9.dist-info/METADATA
cityhero-0.0.9.dist-info/WHEEL
cityhero-0.0.9.dist-info/top_level.txt
cityhero-0.0.9.dist-info/RECORD
